morseplay/__init__.py
morseplay/morse.py
morseplay-0.1.2.dist-info/METADATA
morseplay-0.1.2.dist-info/RECORD
morseplay-0.1.2.dist-info/WHEEL
morseplay-0.1.2.dist-info/top_level.txt
