Metadata-Version: 2.1
Name: morseplay
Version: 0.1.2
Summary: Python library to send and receive morse codes on Raspberry Pi
Home-page: https://www.github.com/ritiek/morseplay
Author: Ritiek Malhotra
Author-email: ritiekmalhotra123@gmail.com
License: MIT
Download-URL: https://github.com/ritiek/morseplay/archive/v0.1.2.tar.gz
Keywords: morse,raspberry-pi,python,LED
Platform: UNKNOWN
Requires-Dist: morse-talk
